pathobj_handler/__init__.py
pathobj_handler/base.py
pathobj_handler/tool.py
pathobj_handler/filestem/__init__.py
pathobj_handler/filestem/filter.py
pathobj_handler/filestem/picker.py
pathobj_handler/filestem/renamer.py
pathobj_handler-1.0.1.dist-info/METADATA
pathobj_handler-1.0.1.dist-info/WHEEL
pathobj_handler-1.0.1.dist-info/top_level.txt
pathobj_handler-1.0.1.dist-info/RECORD
