Metadata-Version: 2.1
Name: pathobj_handler
Version: 1.0.1
Home-page: https://github.com/toritamantaro/path-object-handler
Author: toritamantaro
License: MIT
Requires-Python: >=3.9
Requires-Dist: python-dateutil
